Workbook

Sheet 分组报价表
A1: 主表｜厂家分组询价与报价填写
A2: 填写黄色列。共18组：3组温湿度双控 + 15组湿度控制；型号相同但不同目标值或安装方式需差异报价时，请另列明细。
A3: 说明：数量由逐柜清单公式统计；RH设定要求因柜而异。单价建议报人民币含税出厂价，运费/安装费/认证费用请单独列示。
A4: 设备类别 | B4: 展柜容积(m³) | C4: 客户目标值 / 条件 | D4: 数量(台) | E4: 设备安装位置（涉及） | F4: 推荐型号 | G4: 含税单价RMB | H4: 报价小计RMB | I4: 交期（天） | J4: 外形尺寸mm（厂填）
A5: 温湿度双控 | B5: 0.25 | C5: 18°C；RH 25% | D5: =COUNTIFS('48台逐柜清单'!$B$5:$B$52,A5,'48台逐柜清单'!$F$5:$F$52,B5) -> 1 | E5: 墙面展柜背部 | H5: =IF(G5="","",D5*G5)
A6: 温湿度双控 | B6: 0.45 | C6: 18°C；RH 60% | D6: =COUNTIFS('48台逐柜清单'!$B$5:$B$52,A6,'48台逐柜清单'!$F$5:$F$52,B6) -> 1 | E6: 独立式展柜内部上方夹层 | H6: =IF(G6="","",D6*G6)
A7: 温湿度双控 | B7: 1 | C7: 18°C；RH 25% | D7: =COUNTIFS('48台逐柜清单'!$B$5:$B$52,A7,'48台逐柜清单'!$F$5:$F$52,B7) -> 1 | E7: 墙面展柜背部 | H7: =IF(G7="","",D7*G7)
A8: 仅湿度控制 | B8: 0.15 | C8: RH 25% | D8: =COUNTIFS('48台逐柜清单'!$B$5:$B$52,A8,'48台逐柜清单'!$F$5:$F$52,B8) -> 2 | E8: 墙面展柜背部 | H8: =IF(G8="","",D8*G8)
A9: 仅湿度控制 | B9: 0.2 | C9: RH 55% | D9: =COUNTIFS('48台逐柜清单'!$B$5:$B$52,A9,'48台逐柜清单'!$F$5:$F$52,B9) -> 1 | E9: 墙面展柜背部 | H9: =IF(G9="","",D9*G9)
A10: 仅湿度控制 | B10: 0.25 | C10: RH 25% | D10: =COUNTIFS('48台逐柜清单'!$B$5:$B$52,A10,'48台逐柜清单'!$F$5:$F$52,B10) -> 1 | E10: 桌式展柜内部底座 | H10: =IF(G10="","",D10*G10)
A11: 仅湿度控制 | B11: 0.35 | C11: RH 25,30,45,50,60% | D11: =COUNTIFS('48台逐柜清单'!$B$5:$B$52,A11,'48台逐柜清单'!$F$5:$F$52,B11) -> 8 | E11: 墙面展柜背部、桌式展柜内部底座 | H11: =IF(G11="","",D11*G11)
A12: 仅湿度控制 | B12: 0.45 | C12: RH 30,45,55% | D12: =COUNTIFS('48台逐柜清单'!$B$5:$B$52,A12,'48台逐柜清单'!$F$5:$F$52,B12) -> 5 | E12: 墙面展柜背部、桌式展柜内部底座 | H12: =IF(G12="","",D12*G12)
A13: 仅湿度控制 | B13: 0.5 | C13: RH 25,40,45,50% | D13: =COUNTIFS('48台逐柜清单'!$B$5:$B$52,A13,'48台逐柜清单'!$F$5:$F$52,B13) -> 6 | E13: 墙面展柜背部 | H13: =IF(G13="","",D13*G13)
A14: 仅湿度控制 | B14: 0.6 | C14: RH 30,35,40,45,55,60,65% | D14: =COUNTIFS('48台逐柜清单'!$B$5:$B$52,A14,'48台逐柜清单'!$F$5:$F$52,B14) -> 9 | E14: 墙面展柜背部、桌式展柜内部底座 | H14: =IF(G14="","",D14*G14)
A15: 仅湿度控制 | B15: 0.75 | C15: RH 25,30,40,60% | D15: =COUNTIFS('48台逐柜清单'!$B$5:$B$52,A15,'48台逐柜清单'!$F$5:$F$52,B15) -> 5 | E15: 墙面展柜背部 | H15: =IF(G15="","",D15*G15)
A16: 仅湿度控制 | B16: 1 | C16: RH 40% | D16: =COUNTIFS('48台逐柜清单'!$B$5:$B$52,A16,'48台逐柜清单'!$F$5:$F$52,B16) -> 1 | E16: 墙面展柜背部 | H16: =IF(G16="","",D16*G16)
... A22: 仅湿度控制 | B22: 3.3 | C22: RH 45% | D22: =COUNTIFS('48台逐柜清单'!$B$5:$B$52,A22,'48台逐柜清单'!$F$5:$F$52,B22) -> 2 | E22: 墙面展柜背部 | H22: =IF(G22="","",D22*G22)
A24: 报价补充信息（厂家填写）
A25: 报价厂家/联系人： | F25: 请注明是否含税、运费、出口包装、欧洲配送、安装调试
A26: 报价日期及有效期： | F26: 请确认可适用于西班牙使用环境，最终供电条件待业主确认
A27: 价格条款： | F27: 请列明现有CE/DoC等可提供文件，不应将未提供的证书视为已具备
A28: 电源要求： | F28: 请列明开模/开发费、最小起订量、单柜安装附件费用
A29: 认证/文件： | F29: 请说明滤材/耗材/补水/排水/维护周期及年度维护成本和质保
A30: 如需特殊定制：
A31: 售后与耗材：

Sheet 48台逐柜清单
A1: 附件一｜48台设备逐柜参数清单
A2: 每行对应1台设备；T和RH为客户提供的设定值，展柜容积均为约数。黄色列由厂家按需填写。
A3: 说明：空白温度项＝客户未提出温控要求，并非明确要求无需温控；设备主机实际尺寸与工程边界条件待确认。
A4: 归档编号 | B4: 设备类别 | C4: 原清单序号 | D4: 展柜识别编码 | E4: 展陈名称（原文） | F4: 展柜容积(m³) | G4: 目标温度(°C) | H4: 目标湿度(%RH) | I4: 控制设备安装位置 | J4: 厂家推荐机型 | K4: 逐台特殊备注 | L4: 厂家单台价(元，选填)
A5: TH-01 | B5: 温湿度双控 | C5: 1 | D5: AII SA 2V | E5: Armas para una conquista | F5: 1 | G5: 18 | H5: 25 | I5: 墙面展柜背部
A6: TH-02 | B6: 温湿度双控 | C6: 2 | D6: AII SA 3V | E6: Edicto de Bembibre | F6: 0.25 | G6: 18 | H6: 25 | I6: 墙面展柜背部
A7: TH-03 | B7: 温湿度双控 | C7: 3 | D7: AIV SA 4V | E7: El Cristo de Carrizo | F7: 0.45 | G7: 18 | H7: 60 | I7: 独立式展柜内部上方夹层
A8: RH-01 | B8: 仅湿度控制 | C8: 1 | D8: AI SB 1V | E8: Calcolítico y Edad del Bronce | F8: 0.35 | H8: 25 | I8: 墙面展柜背部
A9: RH-02 | B9: 仅湿度控制 | C9: 2 | D9: AI SB 2VM | E9: Calcolítico y Edad del Bronce | F9: 0.25 | H9: 25 | I9: 桌式展柜内部底座
A10: RH-03 | B10: 仅湿度控制 | C10: 3 | D10: AI SC 1V (↓) | E10: I Edad del Hierro | F10: 0.5 | H10: 40 | I10: 墙面展柜背部
A11: RH-04 | B11: 仅湿度控制 | C11: 4 | D11: AI SC 2V | E11: II Edad del Hierro | F11: 0.75 | H11: 30 | I11: 墙面展柜背部
A12: RH-05 | B12: 仅湿度控制 | C12: 5 | D12: AI SC 3VC | E12: Orfebrería indígena | F12: 1.8 | H12: 25 | I12: 组合式展柜内部底座
A13: RH-06 | B13: 仅湿度控制 | C13: 6 | D13: AI SD 1V | E13: Minería y metalurgia prehistórica y romana | F13: 0.75 | H13: 25 | I13: 墙面展柜背部
A14: RH-07 | B14: 仅湿度控制 | C14: 7 | D14: AI SD 2VM | E14: Depósito de Valdevimbre | F14: 0.35 | H14: 25 | I14: 桌式展柜内部底座
A15: RH-08 | B15: 仅湿度控制 | C15: 8 | D15: AI SLE 1V (↑) | E15: El Castro de Chano | F15: 0.15 | H15: 25 | I15: 墙面展柜背部
A16: RH-09 | B16: 仅湿度控制 | C16: 9 | D16: AI SLE 1V' (↓) | E16: El Castro de Chano | F16: 0.15 | H16: 25 | I16: 墙面展柜背部
A17: RH-10 | B17: 仅湿度控制 | C17: 10 | D17: AII SA 1V | E17: El oro de Roma | F17: 0.35 | H17: 30 | I17: 墙面展柜背部
A18: RH-11 | B18: 仅湿度控制 | C18: 11 | D18: AII SB 1V (↑) | E18: Vida cotidiana | F18: 0.75 | H18: 30 | I18: 墙面展柜背部
A19: RH-12 | B19: 仅湿度控制 | C19: 12 | D19: AII SB 1V' (↓) | E19: Vida cotidiana | F19: 0.75 | H19: 40 | I19: 墙面展柜背部
... A52: RH-45 | B52: 仅湿度控制 | C52: 45 | D52: AVII SC 1VM | E52: Vida cotidiana en la Edad Moderna | F52: 0.35 | H52: 50 | I52: 桌式展柜内部底座
